beam_search/__init__.py
beam_search/beam_search.py
beam_search_bb-0.1.dist-info/METADATA
beam_search_bb-0.1.dist-info/WHEEL
beam_search_bb-0.1.dist-info/top_level.txt
beam_search_bb-0.1.dist-info/RECORD
