Metadata-Version: 2.4
Name: beam_search_BB
Version: 0.1
Summary: A custom beam search decoding algorithm for Pytorch
Author: Balthazar Bujard
Author-email: balthazar.bujard@ircam.fr
Requires-Dist: numpy
Requires-Dist: torch
Dynamic: author
Dynamic: author-email
Dynamic: requires-dist
Dynamic: summary
